LICENSE
MANIFEST.in
README.md
ez_setup.py
setup.cfg
setup.py
nose_greenlet_profiler/__init__.py
nose_greenlet_profiler.egg-info/PKG-INFO
nose_greenlet_profiler.egg-info/SOURCES.txt
nose_greenlet_profiler.egg-info/dependency_links.txt
nose_greenlet_profiler.egg-info/entry_points.txt
nose_greenlet_profiler.egg-info/not-zip-safe
nose_greenlet_profiler.egg-info/requires.txt
nose_greenlet_profiler.egg-info/top_level.txt