Metadata-Version: 1.1
Name: nose-greenlet-profiler
Version: 1.0.2
Summary: GreenletProfiler plugin for Nose
Home-page: https://github.com/sgrankin/nose_greenlet_profiler
Author: Sergey Grankin
Author-email: UNKNOWN
License: UNKNOWN
Platform: UNKNOWN
Classifier: Development Status :: 4 - Beta
Classifier: Intended Audience :: Developers
Classifier: License :: OSI Approved :: MIT License
Classifier: Topic :: Software Development
